iesopt/__init__.py
iesopt/config.py
iesopt/iesopt.py
iesopt/model.py
iesopt/results.py
iesopt/alg/__init__.py
iesopt/alg/algorithm.py
iesopt/alg/mga/__init__.py
iesopt/alg/mga/nvp.py
iesopt/alg/mga/util.py
iesopt/julia/__init__.py
iesopt/julia/general.py
iesopt/julia/setup.py
iesopt/julia/util.py
iesopt/util/__init__.py
iesopt/util/logging.py
iesopt/util/util.py
iesopt-2.11.0.dist-info/METADATA
iesopt-2.11.0.dist-info/WHEEL
iesopt-2.11.0.dist-info/licenses/LICENSE
iesopt-2.11.0.dist-info/RECORD
