Metadata-Version: 2.4
Name: iesopt
Version: 2.11.0
Summary: IESopt -- an Integrated Energy System Optimization framework.
Project-URL: Homepage, https://github.com/ait-energy/iesopt
Project-URL: Documentation, https://ait-energy.github.io/iesopt
Project-URL: Repository, https://github.com/ait-energy/iesopt
Project-URL: Issues, https://github.com/ait-energy/iesopt/issues
Author-email: Stefan Strömer <8915976+sstroemer@users.noreply.github.com>
Maintainer-email: Stefan Strömer <8915976+sstroemer@users.noreply.github.com>
License: MIT
License-File: LICENSE
Keywords: energy model,integrated energy systems,modelling,optimization
Classifier: Development Status :: 5 - Production/Stable
Classifier: Intended Audience :: Science/Research
Classifier: License :: OSI Approved :: MIT License
Classifier: Programming Language :: Python :: 3.10
Classifier: Programming Language :: Python :: 3.11
Classifier: Programming Language :: Python :: 3.12
Classifier: Programming Language :: Python :: 3.13
Requires-Python: >=3.10
Requires-Dist: juliacall==0.9.28
Requires-Dist: juliapkg==0.1.19
Requires-Dist: pandas>=2.0.0
Requires-Dist: pathlib>=1.0.0
Requires-Dist: pydantic>=2.7.4
Requires-Dist: python-dotenv>=1.0.1
